rusty_img_utils-0.3.1.dist-info/METADATA
rusty_img_utils-0.3.1.dist-info/WHEEL
img_utils/__init__.py
img_utils/darken.py
img_utils/utils.py
img_utils/extract.py
img_utils/img_utils.cpython-36m-darwin.so
rusty_img_utils-0.3.1.dist-info/RECORD
