Metadata-Version: 2.1
Name: rusty-img-utils
Version: 0.3.1
Summary: Image utilities with python bindings
Author: Axel Örn Sigurðsson <rusty@absalon.dev>
Author-Email: Axel Örn Sigurðsson <rusty@absalon.dev>
License: MIT
